{
    "results":[
        {
            "id":1,
            "img1":"./recursos-Tarjetas/img1.png",
            "tipo":"CASA",
            "estado":"PARA VENTA",
            "rayo":"ϟ",
            "precio":"900,000.00",
            "cora":"♥",
            "flechas":"⇄",
            "img2":"./recursos-Tarjetas/punteroNavegacion.png",
            "localidad":"Newport Beach, CA",
            "descripcion":"2710 Hilltop Dr, Newport Beach, CA 92660, USA",
            "img3":"./recursos-Tarjetas/perfil.png",
            "name":"Brianne Smith",
            "publicado":"4 months ago",
            "area":"./recursos-Tarjetas/Area.png",
            "habitaciones":"./recursos-Tarjetas/cuartos.png"
        },{
            "id":2,
            "img1":"./recursos-Tarjetas/img2.png",
            "tipo":"CASA",
            "estado":"PARA RENTAR",
            "rayo":"ϟ",
            "precio":"160,000.00",
            "cora":"♥",
            "flechas":"⇄",
            "img2":"./recursos-Tarjetas/punteroNavegacion.png",
            "localidad":"Mission Viejo, CA",
            "descripcion":"26502 Vía Cuervo, CA 92691, USA",
            "img3":"./recursos-Tarjetas/perfil.png",
            "name":"Lionel Richie",
            "publicado":"2 months ago",
            "area":"./recursos-Tarjetas/Area.png",
            "habitaciones":"./recursos-Tarjetas/cuartos.png"
        },{
            "id":3,
            "img1":"./recursos-Tarjetas/img3.png",
            "tipo":"CASA",
            "estado":"PARA RENTAR",
            "rayo":"ϟ",
            "precio":"225,000.00",
            "cora":"♥",
            "flechas":"⇄",
            "img2":"./recursos-Tarjetas/punteroNavegacion.png",
            "localidad":"Beverly Hills, CA",
            "descripcion":"272 S Rexford Dr, Beverly Hills, CA 90212, USA",
            "img3":"./recursos-Tarjetas/perfil.png",
            "name":"Brianne Smith",
            "publicado":"5 months ago",
            "area":"./recursos-Tarjetas/Area.png",
            "habitaciones":"./recursos-Tarjetas/cuartos.png"
        },{
            "id":4,
            "img1":"./recursos-Tarjetas/img4.png",
            "tipo":"TORRE",
            "estado":"PARA RENTAR",
            "rayo":"ϟ",
            "precio":"1'700,000.00",
            "cora":"♥",
            "flechas":"⇄",
            "img2":"./recursos-Tarjetas/punteroNavegacion.png",
            "localidad":"Los Angeles, CA",
            "descripcion":"15 Apartments of Type B",
            "img3":"./recursos-Tarjetas/perfil.png",
            "name":"Lionel Richie",
            "publicado":"8 months ago",
            "area":"./recursos-Tarjetas/Area.png",
            "habitaciones":"./recursos-Tarjetas/cuartos.png"
        },{
            "id":5,
            "img1":"./recursos-Tarjetas/img5.png",
            "tipo":"TORRE",
            "estado":"PARA VENTA",
            "rayo":"ϟ",
            "precio":"310,000.00",
            "cora":"♥",
            "flechas":"⇄",
            "img2":"./recursos-Tarjetas/punteroNavegacion.png",
            "localidad":"Los Angeles, CA",
            "descripcion":"14 Apartments of Type A",
            "img3":"./recursos-Tarjetas/perfil.png",
            "name":"Rachel Dawes",
            "publicado":"2 months ago",
            "area":"./recursos-Tarjetas/Area.png",
            "habitaciones":"./recursos-Tarjetas/cuartos.png"
        },{
            "id":6,
            "img1":"./recursos-Tarjetas/img6.png",
            "tipo":"VERANO",
            "estado":"PARA RENTAR",
            "rayo":"ϟ",
            "precio":"1'300,000.00",
            "cora":"♥",
            "flechas":"⇄",
            "img2":"./recursos-Tarjetas/punteroNavegacion.png",
            "localidad":" Pasadena, CA",
            "descripcion":"Countryside Modern Summer House",
            "img3":"./recursos-Tarjetas/perfil.png",
            "name":"Rachel Dawes",
            "publicado":"4 months ago",
            "area":"./recursos-Tarjetas/Area.png",
            "habitaciones":"./recursos-Tarjetas/cuartos.png"
        }
    ]
}